mmcr/__init__.py
mmcr/mmcr.py
mmcr-0.1.0.dist-info/METADATA
mmcr-0.1.0.dist-info/WHEEL
mmcr-0.1.0.dist-info/top_level.txt
mmcr-0.1.0.dist-info/RECORD
