Metadata-Version: 2.1
Name: mmcr
Version: 0.1.0
Summary: MMCR Loss: Learning efficient coding of natural images with maximum manifold capacity representations
Home-page: https://github.com/skyil7/mmcr
Author: Gio Paik
Keywords: torch,loss,mmcr,Maximum Manifold Capacity Representations
Classifier: Programming Language :: Python :: 3
Classifier: License :: OSI Approved :: MIT License
Classifier: Operating System :: OS Independent
Requires-Dist: einops
